pypages.py
setup.cfg
setup.py
PyPages.egg-info/SOURCES.txt
pypages.egg-info/PKG-INFO
pypages.egg-info/SOURCES.txt
pypages.egg-info/dependency_links.txt
pypages.egg-info/not-zip-safe
pypages.egg-info/top_level.txt