Metadata-Version: 1.1
Name: PyPages
Version: 0.1
Summary: Python Pagination for Humans
Home-page: https://github.com/fengsp/pypages
Author: Shipeng Feng
Author-email: fsp261@gmail.com
License: BSD
Platform: any
Classifier: Intended Audience :: Developers
Classifier: License :: OSI Approved :: BSD License
Classifier: Operating System :: OS Independent
Classifier: Programming Language :: Python
Classifier: Topic :: Software Development :: Libraries :: Python Modules
